odoo10_addon_contract_digitized_signature-10.0.1.0.0-py2.7-nspkg.pth
odoo/addons/contract_digitized_signature/README.rst
odoo/addons/contract_digitized_signature/__init__.py
odoo/addons/contract_digitized_signature/__manifest__.py
odoo/addons/contract_digitized_signature/i18n/es.po
odoo/addons/contract_digitized_signature/models/__init__.py
odoo/addons/contract_digitized_signature/models/account_analytic_account.py
odoo/addons/contract_digitized_signature/report/report_contract.xml
odoo/addons/contract_digitized_signature/static/description/icon.png
odoo/addons/contract_digitized_signature/tests/__init__.py
odoo/addons/contract_digitized_signature/tests/test_contract_tracking.py
odoo/addons/contract_digitized_signature/views/contract_views.xml
odoo10_addon_contract_digitized_signature-10.0.1.0.0.dist-info/DESCRIPTION.rst
odoo10_addon_contract_digitized_signature-10.0.1.0.0.dist-info/METADATA
odoo10_addon_contract_digitized_signature-10.0.1.0.0.dist-info/RECORD
odoo10_addon_contract_digitized_signature-10.0.1.0.0.dist-info/WHEEL
odoo10_addon_contract_digitized_signature-10.0.1.0.0.dist-info/metadata.json
odoo10_addon_contract_digitized_signature-10.0.1.0.0.dist-info/namespace_packages.txt
odoo10_addon_contract_digitized_signature-10.0.1.0.0.dist-info/top_level.txt
