Metadata-Version: 2.0
Name: odoo10-addon-contract-digitized-signature
Version: 10.0.1.0.0
Summary: Contract Digitized Signature
Home-page: https://www.tecnativa.com
Author: Tecnativa, Odoo Community Association (OCA)
Author-email: support@odoo-community.org
License: AGPL-3
Platform: UNKNOWN
Classifier: Programming Language :: Python
Classifier: Framework :: Odoo
Classifier: License :: OSI Approved :: GNU Affero General Public License v3
Requires-Python: ~=2.7
Requires-Dist: odoo (<10.1dev,>=10.0)
Requires-Dist: odoo10-addon-contract
Requires-Dist: odoo10-addon-web-widget-digitized-signature
